qqmail/__init__.py
qqmail-1.0.dist-info/METADATA
qqmail-1.0.dist-info/WHEEL
qqmail-1.0.dist-info/top_level.txt
qqmail-1.0.dist-info/RECORD
