Metadata-Version: 2.1
Name: qqmail
Version: 1.0
Summary: Send your mail ordinary!
Home-page: UNKNOWN
Author: DY_XiaoDong
Author-email: xiaodong@indouyin.cn
License: MIT
Platform: UNKNOWN
Requires: smtplib
